ibis_badge/__init__.py
ibis_badge/_modidx.py
ibis_badge/badge.py
ibis_badge-0.0.1.dist-info/LICENSE
ibis_badge-0.0.1.dist-info/METADATA
ibis_badge-0.0.1.dist-info/WHEEL
ibis_badge-0.0.1.dist-info/entry_points.txt
ibis_badge-0.0.1.dist-info/top_level.txt
ibis_badge-0.0.1.dist-info/RECORD
